[
  {
    "OutputDate": "2022-03-03T00:00:00",
    "PortfolioValue": 1.6497464059905966,
    "Delta": [
      -0.08111675638862936,
      0.34548230244555994,
      0.00970910023292858,
      0.005952898381523626
    ],
    "DeltaStdDev": [
      0.0096697946046844,
      0.005561748779917488,
      0.001246139284076624,
      0.0008417596893331551
    ],
    "Price": 1.6497464059905966,
    "PriceStdDev": 0.013108985947000202
  },
  {
    "OutputDate": "2022-05-04T00:00:00",
    "PortfolioValue": 1.8240406890180545,
    "Delta": [
      0,
      0,
      0,
      0
    ],
    "DeltaStdDev": [
      0,
      0,
      0,
      0
    ],
    "Price": 0.46197142900010507,
    "PriceStdDev": 3.0328530724417596E-09
  },
  {
    "OutputDate": "2022-07-01T00:00:00",
    "PortfolioValue": 1.82708329163095,
    "Delta": [
      0,
      0,
      0,
      0
    ],
    "DeltaStdDev": [
      0,
      0,
      0,
      0
    ],
    "Price": 0.46274202336536463,
    "PriceStdDev": 3.0378823038749567E-09
  },
  {
    "OutputDate": "2022-08-30T00:00:00",
    "PortfolioValue": 1.8301309694763848,
    "Delta": [
      0,
      0,
      0,
      0
    ],
    "DeltaStdDev": [
      0,
      0,
      0,
      0
    ],
    "Price": 0.4635139031254311,
    "PriceStdDev": 3.0429032231363858E-09
  },
  {
    "OutputDate": "2022-10-27T00:00:00",
    "PortfolioValue": 1.833183731020134,
    "Delta": [
      0,
      0,
      0,
      0
    ],
    "DeltaStdDev": [
      0,
      0,
      0,
      0
    ],
    "Price": 0.46428707042441536,
    "PriceStdDev": 3.048371157866535E-09
  },
  {
    "OutputDate": "2022-12-27T00:00:00",
    "PortfolioValue": 1.8362415847420928,
    "Delta": [
      0,
      0,
      0,
      0
    ],
    "DeltaStdDev": [
      0,
      0,
      0,
      0
    ],
    "Price": 0.46506152741000495,
    "PriceStdDev": 3.052920289121252E-09
  }
]